Metadata-Version: 1.1
Name: distributedchat
Version: 0.9.2
Summary: .
Home-page: https://github.com/pklejch/distributed-chat
Author: Petr Klejch
Author-email: klejcpet@fit.cvut.cz
License: GPL-3.0
Keywords: distributed algorithm,chat,chang roberts
Platform: UNKNOWN
Classifier: Intended Audience :: Developers
Classifier: Operating System :: POSIX :: Linux
Classifier: Programming Language :: Python :: 3.5
Classifier: Development Status :: 3 - Alpha
Classifier: License :: OSI Approved :: GNU General Public License v3 (GPLv3)
Classifier: Programming Language :: Python :: Implementation :: CPython
